leet_stats/__init__.py
leet_stats/__main__.py
leet_stats/api.py
leet_stats/cli.py
leet_stats/display.py
leet_stats/friends.py
leet_stats-1.0.0.dist-info/licenses/LICENSE
leet_stats-1.0.0.dist-info/METADATA
leet_stats-1.0.0.dist-info/WHEEL
leet_stats-1.0.0.dist-info/entry_points.txt
leet_stats-1.0.0.dist-info/top_level.txt
leet_stats-1.0.0.dist-info/RECORD
